Wjp_bigdata3.py
WJp_bigdata3-1.0.dist-info/METADATA
WJp_bigdata3-1.0.dist-info/WHEEL
WJp_bigdata3-1.0.dist-info/top_level.txt
WJp_bigdata3-1.0.dist-info/RECORD
