Metadata-Version: 2.1
Name: WJp-bigdata3
Version: 1.0
Summary: 大数据3Wjp
Home-page: UNKNOWN
Author: Wjp
Author-email: 2878508824@qq.com
License: UNKNOWN
Platform: UNKNOWN
